gensql_magics/__init__.py
gensql_magics/gensql.jar
gensql_magics/magic.py
gensql_magics-0.0.4.dist-info/WHEEL
gensql_magics-0.0.4.dist-info/entry_points.txt
gensql_magics-0.0.4.dist-info/METADATA
gensql_magics-0.0.4.dist-info/RECORD
